<?xml version="1.0"?>
<!DOCTYPE hibernate-mapping PUBLIC "-//Hibernate/Hibernate Mapping DTD 3.0//EN"
"http://www.hibernate.org/dtd/hibernate-mapping-3.0.dtd">
<!-- Generated Mar 25, 2018 2:40:18 PM by Hibernate Tools 4.3.1 -->
<hibernate-mapping>
    <class name="hust.sie.inpg12.sonnc.entities.GiangVienPhuTrach" table="giang_vien_phu_trach" catalog="doantotnghiep" optimistic-lock="version">
        <id name="maGvpt" type="java.lang.Integer">
            <column name="ma_gvpt" />
            <generator class="identity" />
        </id>
        <property name="email" type="string">
            <column name="email" not-null="true" />
        </many-to-one>
        <property name="hoTen" type="string">
            <column name="ho_ten" not-null="true" />
        </property>
        <property name="diaChi" type="string">
            <column name="dia_chi" length="500" not-null="true" />
        </property>
        <property name="dienThoai" type="string">
            <column name="dien_thoai" length="15" not-null="true" />
        </property>
        <property name="khoaVien" type="string">
            <column name="khoa_vien" length="500" />
        </property>
        <property name="boMon" type="string">
            <column name="bo_mon" length="500" />
        </property>
        <property name="congTrinhNghienCuu" type="string">
            <column name="cong_trinh_nghien_cuu" length="65535" />
        </property>
        <property name="sachXuatBan" type="string">
            <column name="sach_xuat_ban" length="65535" />
        </property>
        <property name="monGiangDay" type="string">
            <column name="mon_giang_day" length="65535" />
        </property>
        <property name="khac" type="string">
            <column name="khac" length="65535" />
        </property>
        <property name="avatar" type="string">
            <column name="avatar" length="500" />
        </property>
    </class>
</hibernate-mapping>
